{"stat.walkOneCm":9259,"stat.boatOneCm":624,"stat.craftItem.minecraft.planks":16,"stat.killEntity.Chicken":3,"stat.leaveGame":1,"stat.pickup.minecraft.crafting_table":1,"stat.mineBlock.minecraft.log2":6,"stat.damageTaken":20,"stat.mineBlock.minecraft.crafting_table":1,"stat.pickup.minecraft.feather":6,"stat.craftItem.minecraft.crafting_table":1,"stat.mobKills":3,"stat.craftItem.minecraft.boat":1,"stat.mineBlock.minecraft.log":4,"stat.pickup.minecraft.log2":6,"stat.pickup.minecraft.log":4,"stat.flyOneCm":16270,"stat.useItem.minecraft.boat":1,"stat.jump":82,"stat.mineBlock.minecraft.leaves":1,"stat.swimOneCm":1029,"stat.playOneMinute":4665,"stat.fallOneCm":1213,"stat.useItem.minecraft.stone_axe":16,"stat.damageDealt":120,"stat.pickup.minecraft.chicken":3,"stat.timeSinceDeath":4665,"stat.pickup.minecraft.sapling":1,"stat.sprintOneCm":16942,"stat.useItem.minecraft.crafting_table":1,"stat.diveOneCm":368,"stat.craftItem.minecraft.stick":8,"stat.craftingTableInteraction":1}